NewFunctionsPYC/__init__.py
NewFunctionsPYC/embed.py
NewFunctionsPYC/loader.py
NewFunctionsPYC/commands/hybrid.py
NewFunctionsPYC/commands/prefix.py
NewFunctionsPYC/commands/slash.py
NewFunctionsPYC-1.3.0.dist-info/METADATA
NewFunctionsPYC-1.3.0.dist-info/WHEEL
NewFunctionsPYC-1.3.0.dist-info/top_level.txt
NewFunctionsPYC-1.3.0.dist-info/RECORD
