Metadata-Version: 2.1
Name: NewFunctionsPYC
Version: 1.3.0
Summary: :A simple library for add new functions the Pycord
Author: Marciel404
License: MIT
Project-URL: Homepage, https://github.com/Marciel404/NewFunctionsPYC
Keywords: Pycord BetterFunctions
Classifier: License :: OSI Approved :: MIT License
Classifier: Intended Audience :: Developers
Classifier: Natural Language :: Portuguese
Classifier: Operating System :: OS Independent
Classifier: Programming Language :: Python :: 3.10
Classifier: Programming Language :: Python :: 3.11
Classifier: Topic :: Software Development :: Libraries
Classifier: Topic :: Software Development :: Libraries :: Python Modules
Classifier: Topic :: Utilities
Classifier: Typing :: Typed
Requires-Python: >=3.9
Requires-Dist: py-cord
Requires-Dist: hexacolors
